Artur_serializer/__init__.py
Artur_serializer/constants.py
Artur_serializer/json_serializer.py
Artur_serializer/serialiser.py
Artur_serializer/serializer_zavod.py
Artur_serializer/xml_serializer.py
Artur_serializer-0.1.0.dist-info/METADATA
Artur_serializer-0.1.0.dist-info/WHEEL
Artur_serializer-0.1.0.dist-info/top_level.txt
Artur_serializer-0.1.0.dist-info/RECORD
