Metadata-Version: 2.1
Name: Artur-serializer
Version: 0.1.0
Summary: somme serialization
Author: Artur Kudlasevich
Author-email: artur.kudlasewitsch@gmail.com
License: MIT
Classifier: Intended Audience :: Developers
Classifier: License :: OSI Approved :: MIT License
Classifier: Programming Language :: Python :: 3.10
Classifier: Operating System :: OS Independent
Requires-Dist: regex
